lp_backup/__init__.py
lp_backup/exceptions.py
lp_backup/file_io.py
lp_backup/interface.py
lp_backup/runner.py
lp_backup-0.1.11.dist-info/LICENSE
lp_backup-0.1.11.dist-info/WHEEL
lp_backup-0.1.11.dist-info/METADATA
lp_backup-0.1.11.dist-info/RECORD
