Metadata-Version: 2.1
Name: lp-backup
Version: 0.1.11
Summary: Script to create local backups from Lastpass
Home-page: UNKNOWN
License: MIT
Author: Rick Henry
Author-email: fredericmhenry@gmail.com
Requires-Python: >=3.6,<4.0
Classifier: License :: OSI Approved :: MIT License
Classifier: Programming Language :: Python :: 3
Classifier: Programming Language :: Python :: 3.6
Classifier: Programming Language :: Python :: 3.7
Requires-Dist: click (>=7.0,<8.0)
Requires-Dist: cryptography (>=2.4,<3.0)
Requires-Dist: fs (>=2.1,<3.0)
Requires-Dist: fs-s3fs (>=1.0,<2.0)
Requires-Dist: ruamel.yaml (>=0.15.80,<0.16.0)
